PyGMRES
