Metadata-Version: 2.1
Name: PyGMRES
Version: 0.1.1
Summary: A python implementation of the GMRES algorithm
Home-page: https://github.com/ML4FnP/PyGMRES
Author: Johannes Blaschke
Author-email: jpblaschke@lbl.gov
License: UNKNOWN
Platform: UNKNOWN
Classifier: Programming Language :: Python :: 3
Classifier: License :: OSI Approved :: MIT License
Classifier: Operating System :: OS Independent
Requires-Python: >=3.6
